{
  "objectInfo" : {
    "id" : "4Q7dHXhSyjlfHv48qpkQiV",
    "name" : "Mapplet_Base_Affiliation_Group_Configuration_to_Relationship",
    "type" : "DMAPPLET",
    "metadata" : {
      "modelVersion" : {
        "major" : 0,
        "minor" : 0
      },
      "repoInfo" : {
        "repoHandle" : "010P9V40000000000004"
      },
      "contextAttributes" : [ {
        "name" : "id",
        "value" : "@1"
      } ],
      "additionalInfo" : {
        "description" : "",
        "contentType" : "JSON",
        "documentState" : "VALID"
      }
    }
  },
  "dataFileExtension" : "zip",
  "updateTime" : "2023-09-02T00:06:18.305Z",
  "objectRefs" : [ {
    "id" : "5uYmNFMH3iMgjOZOwn57cf",
    "name" : "UDF_NotNullCheck",
    "type" : "UDF",
    "metadata" : {
      "modelVersion" : {
        "major" : 0,
        "minor" : 0
      },
      "repoInfo" : {
        "repoHandle" : "010P9V41000000000004"
      },
      "contextAttributes" : null,
      "additionalInfo" : {
        "description" : "This function checks if the values of the column are not null.\n\nArguments:\ncolumn: [string] Column name on which the check is to be applied.\n\nReturn Type:\n[Numeric] Returns 0 for invalid rows and 1 for valid rows.",
        "contentType" : "JSON",
        "documentState" : "VALID"
      }
    },
    "path" : "/Explore/Shared/User Defined Functions"
  }, {
    "id" : "4EdhAdn3SkkdQ0fsDosfOK",
    "name" : "UDF_IsValidBoolean",
    "type" : "UDF",
    "metadata" : {
      "modelVersion" : {
        "major" : 0,
        "minor" : 0
      },
      "repoInfo" : {
        "repoHandle" : "010P9V41000000000005"
      },
      "contextAttributes" : null,
      "additionalInfo" : {
        "description" : "This function checks if the values of the column are valid boolean or not.\n\nArguments:\ncolumn: [string] Column name on which the check is to be applied.\nboolValue1: [string] Valid boolean value 1 for the column\nboolValue2: [string] Valid boolean value 2 for the column\n\nReturn Type: \n[Numeric] Returns 0 for invalid rows and 1 for valid rows.",
        "contentType" : "JSON",
        "documentState" : "VALID"
      }
    },
    "path" : "/Explore/Shared/User Defined Functions"
  } ]
}